{
	"cmake" : 
	{
		"generator" : 
		{
			"multiConfig" : false,
			"name" : "NMake Makefiles"
		},
		"paths" : 
		{
			"cmake" : "E:/CLion/bin/cmake/win/x64/bin/cmake.exe",
			"cpack" : "E:/CLion/bin/cmake/win/x64/bin/cpack.exe",
			"ctest" : "E:/CLion/bin/cmake/win/x64/bin/ctest.exe",
			"root" : "E:/CLion/bin/cmake/win/x64/share/cmake-3.29"
		},
		"version" : 
		{
			"isDirty" : false,
			"major" : 3,
			"minor" : 29,
			"patch" : 6,
			"string" : "3.29.6",
			"suffix" : ""
		}
	},
	"objects" : 
	[
		{
			"jsonFile" : "codemodel-v2-6aff00dbdf97e1764a67.json",
			"kind" : "codemodel",
			"version" : 
			{
				"major" : 2,
				"minor" : 7
			}
		},
		{
			"jsonFile" : "cache-v2-965f6bb6f5b59ad3f388.json",
			"kind" : "cache",
			"version" : 
			{
				"major" : 2,
				"minor" : 0
			}
		},
		{
			"jsonFile" : "cmakeFiles-v1-fe5e4d2e13ef5087c9aa.json",
			"kind" : "cmakeFiles",
			"version" : 
			{
				"major" : 1,
				"minor" : 0
			}
		},
		{
			"jsonFile" : "toolchains-v1-a616cb1c09ccc7150f69.json",
			"kind" : "toolchains",
			"version" : 
			{
				"major" : 1,
				"minor" : 0
			}
		}
	],
	"reply" : 
	{
		"cache-v2" : 
		{
			"jsonFile" : "cache-v2-965f6bb6f5b59ad3f388.json",
			"kind" : "cache",
			"version" : 
			{
				"major" : 2,
				"minor" : 0
			}
		},
		"cmakeFiles-v1" : 
		{
			"jsonFile" : "cmakeFiles-v1-fe5e4d2e13ef5087c9aa.json",
			"kind" : "cmakeFiles",
			"version" : 
			{
				"major" : 1,
				"minor" : 0
			}
		},
		"codemodel-v2" : 
		{
			"jsonFile" : "codemodel-v2-6aff00dbdf97e1764a67.json",
			"kind" : "codemodel",
			"version" : 
			{
				"major" : 2,
				"minor" : 7
			}
		},
		"toolchains-v1" : 
		{
			"jsonFile" : "toolchains-v1-a616cb1c09ccc7150f69.json",
			"kind" : "toolchains",
			"version" : 
			{
				"major" : 1,
				"minor" : 0
			}
		}
	}
}
